odoo/addons/base_phone_rate_import_bandwith/README.rst
odoo/addons/base_phone_rate_import_bandwith/__init__.py
odoo/addons/base_phone_rate_import_bandwith/__manifest__.py
odoo/addons/base_phone_rate_import_bandwith/demo/bandwith.xlsx
odoo/addons/base_phone_rate_import_bandwith/i18n/base_phone_rate_import_bandwith.pot
odoo/addons/base_phone_rate_import_bandwith/models/__init__.py
odoo/addons/base_phone_rate_import_bandwith/models/phone_rate.py
odoo/addons/base_phone_rate_import_bandwith/readme/CONFIGURE.rst
odoo/addons/base_phone_rate_import_bandwith/readme/CONTRIBUTORS.rst
odoo/addons/base_phone_rate_import_bandwith/readme/DESCRIPTION.rst
odoo/addons/base_phone_rate_import_bandwith/readme/USAGE.rst
odoo/addons/base_phone_rate_import_bandwith/static/description/icon.png
odoo/addons/base_phone_rate_import_bandwith/static/description/index.html
odoo/addons/base_phone_rate_import_bandwith/tests/__init__.py
odoo/addons/base_phone_rate_import_bandwith/tests/test_base_phone_rate_bandwith.py
odoo/addons/base_phone_rate_import_bandwith/wizard/__init__.py
odoo/addons/base_phone_rate_import_bandwith/wizard/base_phone_rate_import.py
odoo/addons/base_phone_rate_import_bandwith/wizard/base_phone_rate_import_view.xml
odoo12_addon_base_phone_rate_import_bandwith-12.0.1.0.1.dist-info/METADATA
odoo12_addon_base_phone_rate_import_bandwith-12.0.1.0.1.dist-info/WHEEL
odoo12_addon_base_phone_rate_import_bandwith-12.0.1.0.1.dist-info/top_level.txt
odoo12_addon_base_phone_rate_import_bandwith-12.0.1.0.1.dist-info/RECORD
